ckanext_dc_view-1.0.2-py3.12-nspkg.pth
ckanext/dc_view/__init__.py
ckanext/dc_view/_version.py
ckanext/dc_view/cli.py
ckanext/dc_view/jobs.py
ckanext/dc_view/meta.py
ckanext/dc_view/plugin.py
ckanext/dc_view/route_funcs.py
ckanext/dc_view/assets/.gitignore
ckanext/dc_view/assets/dc_view.css
ckanext/dc_view/assets/webassets.yml
ckanext/dc_view/templates/.gitignore
ckanext/dc_view/templates/dc_view.html
ckanext/dc_view/tests/__init__.py
ckanext/dc_view/tests/requirements.txt
ckanext/dc_view/tests/test_jobs.py
ckanext/dc_view/tests/test_plugin.py
ckanext/dc_view/tests/test_route.py
ckanext/dc_view/tests/data/calibration_beads_47.rtdc
ckanext_dc_view-1.0.2.dist-info/licenses/LICENSE
ckanext_dc_view-1.0.2.dist-info/METADATA
ckanext_dc_view-1.0.2.dist-info/WHEEL
ckanext_dc_view-1.0.2.dist-info/entry_points.txt
ckanext_dc_view-1.0.2.dist-info/namespace_packages.txt
ckanext_dc_view-1.0.2.dist-info/top_level.txt
ckanext_dc_view-1.0.2.dist-info/RECORD
