Metadata-Version: 2.4
Name: ckanext-dc_view
Version: 1.0.2
Summary: Preview DC data on DCOR
Author: Paul Müller
Maintainer-email: Paul Müller <dev@craban.de>
License: GNU Affero General Public License v3 or later (AGPLv3+)
Project-URL: source, https://github.com/DCOR-dev/ckanext-dc_view
Project-URL: tracker, https://github.com/DCOR-dev/ckanext-dc_view/issues
Project-URL: changelog, https://github.com/DCOR-dev/ckanext-dc_view/blob/main/CHANGELOG
Keywords: DC,DCOR,deformability,cytometry
Classifier: Operating System :: OS Independent
Classifier: Programming Language :: Python :: 3
Classifier: Topic :: Scientific/Engineering :: Visualization
Classifier: Intended Audience :: Science/Research
Requires-Python: <4,>=3.8
License-File: LICENSE
Requires-Dist: ckan<3,>=2.10.4
Requires-Dist: dclab>=0.60.9
Requires-Dist: dcor_shared>=0.12.0
Requires-Dist: matplotlib
Requires-Dist: numpy>=1.19
Requires-Dist: pillow
Dynamic: license-file
